SIMPApy/SIMPA.py
SIMPApy/__init__.py
SIMPApy/analyze.py
SIMPApy/core.py
SIMPApy/preprocess.py
SIMPApy/ranking.py
SIMPApy/visualize.py
simpapy-0.1.6.dist-info/licenses/LICENSE.txt
simpapy-0.1.6.dist-info/METADATA
simpapy-0.1.6.dist-info/WHEEL
simpapy-0.1.6.dist-info/top_level.txt
simpapy-0.1.6.dist-info/RECORD
