Metadata-Version: 2.4
Name: SIMPApy
Version: 0.1.6
Summary: Normalized Single Sample Integrated Multiomics Pathway Analysis
Author-email: Hasan Alsharoh <hasanalsharoh@gmail.com>
License: Apache License (2.0)
Project-URL: Homepage, https://github.com/hasanalsharoh/SIMPApy
Project-URL: Bug Tracker, https://github.com/hasanalsharoh/SIMPApy/issues
Classifier: Programming Language :: Python :: 3
Classifier: License :: OSI Approved :: Apache Software License
Classifier: Operating System :: OS Independent
Classifier: Intended Audience :: Science/Research
Classifier: Topic :: Scientific/Engineering :: Bio-Informatics
Requires-Python: >=3.8
License-File: LICENSE.txt
Requires-Dist: gseapy==1.1.3
Requires-Dist: numpy==1.23.5
Requires-Dist: scipy==1.14.0
Requires-Dist: pandas==2.2.2
Requires-Dist: pydeseq2==0.4.10
Requires-Dist: matplotlib==3.9.2
Requires-Dist: plotly==5.24.1
Requires-Dist: scikit-learn==1.5.1
Requires-Dist: seaborn==0.13.2
Requires-Dist: statsmodels==0.14.1
Requires-Dist: ipywidgets==8.1.5
Requires-Dist: pillow==10.4.0
Requires-Dist: kaleido==0.1.0.post1
Dynamic: license-file
